{
    "sourceFile": "#source/scss/_index.scss",
    "activeCommit": 0,
    "commits": [
        {
            "activePatchIndex": 3,
            "patches": [
                {
                    "date": 1730999145415,
                    "content": "Index: \n===================================================================\n--- \n+++ \n"
                },
                {
                    "date": 1730999157992,
                    "content": "Index: \n===================================================================\n--- \n+++ \n@@ -638,8 +638,9 @@\n }\n \n .filter-sectionwrap.frstsection {\n     padding-top: 90px;\n+    margin-top: 0;\n }\n \n // filter end\n \n"
                },
                {
                    "date": 1731070509437,
                    "content": "Index: \n===================================================================\n--- \n+++ \n@@ -495,11 +495,11 @@\n .selecteltext {\n     @include h6;\n     position: relative;\n     color: var(--primary);\n-    height: 28px;\n+    min-height: 28px;\n     display: flex;\n-    align-items: flex-end;\n+    align-items: center;\n     width: 100%;\n     max-width: 100%;\n     flex: 0 0 100%;\n     cursor: pointer;\n"
                },
                {
                    "date": 1731070560961,
                    "content": "Index: \n===================================================================\n--- \n+++ \n@@ -467,9 +467,9 @@\n .ddmenu {\n     background: #fff;\n     border-radius: 0 0 10px 10px;\n     position: absolute;\n-    top: 32px;\n+    top: 48px;\n     left: 0;\n     box-shadow: 0 7px 12px rgba(#000, 0.3);\n     width: 280px;\n     padding: 16px 12px 12px 12px;\n"
                }
            ],
            "date": 1730999145415,
            "name": "Commit-0",
            "content": ".pagesideline {\n    background: #EEEEEE;\n    position: fixed;\n    width: 128px;\n    z-index: 13;\n    height: 100vh;\n    // display: flex;\n    // flex-direction: column;\n    // justify-content: space-between;\n    // align-items: center;\n    padding: 90px 5px 24px;\n    text-align: center;\n\n    &.pagesideline__left {\n        left: 0;\n        top: 0;\n    }\n\n    &.pagesideline__right {\n        right: 0;\n        top: 0;\n    }\n}\n\n// .loadpage {\n//     header.header {\n//         transform: translateY(-100%);\n//     }\n\n//     .pagesideline.pagesideline__right {\n//         transform: translatex(100%);\n//     }\n\n//     .pagesideline.pagesideline__left {\n//         transform: translatex(-100%);\n//     }\n\n//     .scrollnext {\n//         opacity: 0;\n//         transform: translateY(100px);\n//     }\n\n//     .welcomesection {\n\n//         .containersect {\n//             padding-left: 0;\n//             padding-right: 0;\n//         }\n\n//         .imgwrap {\n//             height: 100vh;\n//             border-radius: 0;\n//             max-height: 100vh;\n\n\n//         }\n//     }\n// }\n\n.leftlogo {\n    transition: 0.3s;\n    filter: brightness(0);\n    margin-bottom: 100px;\n    display: inline-block;\n\n    &:hover {\n        filter: brightness(1);\n    }\n}\n\n.leftsoclist {\n    li {\n        margin-bottom: 14px;\n\n        &:last-child {\n            margin-bottom: 0;\n        }\n\n        a {\n            transition: 0.3s;\n            filter: brightness(0);\n\n            img {\n                width: 24px;\n                vertical-align: top;\n            }\n\n            &:hover {\n                filter: brightness(1);\n            }\n        }\n    }\n}\n\n.languagelist {\n    list-style-type: none;\n\n    li {\n\n        a {\n            text-transform: uppercase;\n            color: var(--primary);\n            font-size: 16px;\n            font-weight: 500;\n            transition: 0.3s;\n            padding: 4px 10px;\n            border-bottom: 1px solid #3D3743;\n            display: inline-block;\n\n            &:hover {\n                color: var(--accent);\n            }\n        }\n\n        &:last-child {\n            a {\n                border-bottom: none;\n            }\n        }\n    }\n}\n\n.welcomesection {\n    position: relative;\n    padding-top: 90px;\n\n    .containersect {\n        transition: 0.5s;\n    }\n\n    .imgwrap {\n        position: relative;\n        border-radius: 16px;\n        overflow: hidden;\n        // height: 600px;\n        height: calc(100vh - 150px);\n        transition: 0.5s;\n        // max-height: calc(100vh - 110px);\n\n        img {\n            width: 100%;\n            height: 100%;\n            object-fit: cover;\n            object-position: 50% 50%;\n            vertical-align: top;\n        }\n    }\n\n    .welcomesection__scrollarr {\n        position: absolute;\n        bottom: 48px;\n        z-index: 2;\n        left: 50%;\n        margin-left: -24px;\n        display: inline-block;\n\n        img {\n            width: 70px;\n            vertical-align: top;\n        }\n    }\n}\n\n\n// filter\n.filter-sectionwrap {\n    margin-top: 80px;\n}\n\n.filter-section {\n    background: #fff;\n    border-radius: 16px;\n    position: relative;\n}\n\n.filter-section__header {\n    ul {\n        display: flex;\n        align-items: center;\n        list-style-type: none;\n\n        li {\n            position: relative;\n\n            &::after {\n                content: '';\n                width: 1px;\n                height: 24px;\n                background: #EEEEEE;\n                border-radius: 8px;\n                position: absolute;\n                right: 0;\n                top: 50%;\n                transform: translateY(-50%)\n            }\n\n            &:last-child {\n                &::after {\n                    display: none;\n                }\n            }\n\n            button {\n                @include h6;\n                color: var(--gray-dark);\n                height: 59px;\n                min-width: 120px;\n                padding: 5px 10px;\n                cursor: pointer;\n                transition: 0.3s;\n\n                &:hover {\n                    color: var(--accent)\n                }\n\n                &.active {\n                    color: var(--accent);\n                }\n            }\n\n\n        }\n    }\n}\n\n.filter-section__body {\n    padding: 16px 0;\n}\n\n.filter__searchboxwrap {\n    padding: 0 16px;\n}\n\n.filter__searchbox {\n    position: relative;\n    margin-bottom: 30px;\n\n    input {\n        width: 100%;\n        height: 56px;\n        border: 1px solid #C3C4C4;\n        padding-left: 48px;\n        padding-right: 15px;\n        border-radius: 12px;\n        font-size: 16px;\n        font-weight: 500;\n        color: #0D0D0D;\n        font-family: \"Libre Franklin\", sans-serif;\n        transition: 0.3s;\n\n        &::placeholder {\n            color: #0D0D0D;\n        }\n\n        &:focus,\n        &:not(:placeholder-shown) {\n            border-color: var(--primary);\n        }\n    }\n\n    .search-ic {\n        position: absolute;\n        width: 24px;\n        left: 16px;\n        top: 50%;\n        transform: translateY(-50%);\n    }\n}\n\n.fscontent {\n    display: flex;\n    flex-wrap: wrap;\n    align-items: center;\n}\n\n.fscontent__type {\n    width: 100%;\n    max-width: calc((100% - 141px) / 4);\n    flex: 0 0 calc((100% - 141px) / 4);\n    padding-left: 16px;\n    padding-right: 5px;\n    position: relative;\n\n    &::after {\n        content: \"\";\n        width: 1px;\n        height: 24px;\n        background: #EEEEEE;\n        border-radius: 8px;\n        position: absolute;\n        right: 0;\n        top: 50%;\n        transform: translateY(-50%);\n    }\n}\n\n.fscontent__bb {\n    width: 100%;\n    max-width: calc((100% - 141px) / 4);\n    flex: 0 0 calc((100% - 141px) / 4);\n    padding-left: 16px;\n    padding-right: 5px;\n    position: relative;\n\n    &::after {\n        content: \"\";\n        width: 1px;\n        height: 24px;\n        background: #EEEEEE;\n        border-radius: 8px;\n        position: absolute;\n        right: 0;\n        top: 50%;\n        transform: translateY(-50%);\n    }\n}\n\n.fscontent__price {\n    width: 100%;\n    max-width: calc((100% - 141px) / 4);\n    flex: 0 0 calc((100% - 141px) / 4);\n    padding-left: 16px;\n    padding-right: 5px;\n    position: relative;\n\n    &::after {\n        content: \"\";\n        width: 1px;\n        height: 24px;\n        background: #EEEEEE;\n        border-radius: 8px;\n        position: absolute;\n        right: 0;\n        top: 50%;\n        transform: translateY(-50%);\n    }\n}\n\n.fscontent__loc {\n    width: 100%;\n    max-width: calc((100% - 141px) / 4);\n    flex: 0 0 calc((100% - 141px) / 4);\n    padding-left: 16px;\n    padding-right: 5px;\n    position: relative;\n\n    p {\n        position: relative;\n        padding-left: 32px;\n        color: var(--primary);\n        font-size: 16px;\n        font-weight: 500;\n        height: 28px;\n        display: flex;\n        align-items: flex-end;\n\n        img {\n            position: absolute;\n            left: 0;\n            top: 3px;\n            width: 24px;\n        }\n    }\n}\n\n.fscontent__btn {\n    width: 100%;\n    max-width: 141px;\n    flex: 0 0 141px;\n    padding-left: 12px;\n    padding-right: 12px;\n\n    input {\n        width: 100%;\n        height: 50px;\n        display: flex;\n        align-items: center;\n        justify-content: center;\n        border-radius: 16px;\n        background: var(--accent);\n        transition: 0.5s;\n        color: #fff;\n        font-size: 16px;\n        font-weight: 500;\n        font-family: \"Libre Franklin\", sans-serif;\n        border: none;\n        cursor: pointer;\n\n        &:hover {\n            box-shadow: 1px 2px 9px rgba(#4900AA, 0.7);\n        }\n    }\n}\n\n.styledselect__wrap {\n    .select2 {\n        width: 100% !important;\n    }\n\n    .select2-container--default .select2-selection--single {\n        border: none;\n        border-radius: 0;\n    }\n\n    .select2-container--default .select2-selection--single .select2-selection__placeholder,\n    .select2-container--default .select2-selection--single .select2-selection__rendered {\n        color: var(--primary);\n        font-size: 16px;\n        font-weight: 500;\n        font-family: \"Libre Franklin\", sans-serif;\n    }\n\n    .select2-container--default .select2-selection--single .select2-selection__arrow b {\n        display: none;\n    }\n\n    .select2-container--default .select2-selection--single .select2-selection__arrow {\n        width: 24px;\n        height: 25px;\n        background: url('../img/general/select-arr.svg') no-repeat center / 100%;\n        transition: 0.3s;\n    }\n\n    .select2-container--default.select2-container--open .select2-selection--single .select2-selection__arrow {\n        transform: rotate(-180deg);\n    }\n\n\n\n}\n\n.select2-dropdown {\n    border: none;\n    box-shadow: 0 7px 12px rgba(#000, 0.3);\n    padding: 8px 4px;\n    border-radius: 0 0 10px 10px;\n}\n\n.select2-results__option {\n    font-size: 14px;\n    color: var(--primary);\n    line-height: 130%;\n    border-radius: 8px;\n    padding: 8px;\n}\n\n.select2-container--default .select2-results__option--highlighted.select2-results__option--selectable {\n    background: #EEEEEE;\n    color: var(--primary);\n}\n\n.select2-container--default .select2-results>.select2-results__options {\n    &::-webkit-scrollbar {\n        width: 6px;\n    }\n\n    &::-webkit-scrollbar-track {\n        // box-shadow: inset 0 0 6px rgba(0, 0, 0, 0.3);\n    }\n\n    &::-webkit-scrollbar-thumb {\n        background-color: rgb(219, 219, 219);\n        border-radius: 8px;\n    }\n}\n\n.ddmenu {\n    background: #fff;\n    border-radius: 0 0 10px 10px;\n    position: absolute;\n    top: 32px;\n    left: 0;\n    box-shadow: 0 7px 12px rgba(#000, 0.3);\n    width: 280px;\n    padding: 16px 12px 12px 12px;\n    display: none;\n    z-index: 3;\n\n    &.price {\n        width: 390px;\n        display: flex;\n        flex-wrap: wrap;\n        margin-left: -4px;\n        margin-right: -4px;\n\n        .ddprce-col {\n            width: 100%;\n            max-width: 50%;\n            flex: 0 0 50%;\n            padding: 0 4px\n        }\n    }\n}\n\n.selecteltext {\n    @include h6;\n    position: relative;\n    color: var(--primary);\n    height: 28px;\n    display: flex;\n    align-items: flex-end;\n    width: 100%;\n    max-width: 100%;\n    flex: 0 0 100%;\n    cursor: pointer;\n    padding-right: 20px;\n\n    &::after {\n        content: '';\n        width: 24px;\n        height: 25px;\n        background: url(../img/general/select-arr.svg) no-repeat center / 100%;\n        -webkit-transition: 0.3s;\n        transition: 0.3s;\n        right: 0;\n        position: absolute;\n    }\n\n    &.active {\n        &::after {\n            transform: rotate(-180deg);\n        }\n    }\n\n    span {\n        text-transform: uppercase;\n        color: var(--gray-dark);\n        display: inline-block;\n        margin-right: 4px;\n    }\n}\n\n.bb-labels {\n    display: flex;\n    flex-wrap: wrap;\n    padding: 0 6px;\n}\n\n.bb-label {\n    margin-right: 6px;\n    margin-bottom: 8px;\n\n    input {\n        display: none;\n\n        &:checked+label {\n            background: #EEEEEE\n        }\n    }\n\n    label {\n        @include body2;\n        color: var(--primary);\n        padding: 7px 15px;\n        border-radius: 8px;\n        border: 1px solid #EEEEEE;\n        cursor: pointer;\n    }\n}\n\n.labksbox {\n    .title {\n        padding: 6px;\n        margin-bottom: 4px;\n        @include body1;\n        color: var(--primary);\n    }\n}\n\n.ddprce-col {\n    .title {\n        padding: 6px;\n        margin-bottom: 16px;\n        font-size: 16px;\n        line-height: 170%;\n        color: var(--primary);\n    }\n\n    .inputfield {\n        position: relative;\n        margin-bottom: 16px;\n\n        input {\n            height: 48px;\n            border: 1px solid #A0A0A0;\n            border-radius: 8px;\n            padding-left: 50px;\n            color: #3D3743;\n            font-size: 16px;\n            font-family: \"Libre Franklin\", sans-serif;\n            width: 100%;\n            transition: 0.3s;\n\n            &:focus {\n                border: 1px solid #0D0D0D;\n            }\n        }\n\n        span {\n            @include body1;\n            position: absolute;\n            text-transform: uppercase;\n            left: 8px;\n            top: 11px;\n            color: var(--gray-dark);\n        }\n    }\n\n    button {\n        font-family: \"Libre Franklin\", sans-serif;\n        height: 50px;\n        border-radius: 16px;\n        width: 100%;\n        font-size: 16px;\n        font-weight: 500;\n        cursor: pointer;\n\n        &.reset {\n            color: var(--primary);\n            border: 1px solid var(--primary);\n        }\n\n        &.apply {\n            color: #fff;\n            background: var(--accent);\n        }\n    }\n}\n\n.fscontent__price {\n    .ddmenu {\n        display: none;\n\n        &.show {\n            display: flex;\n        }\n    }\n}\n\n.filter-sectionwrap.frstsection {\n    padding-top: 90px;\n}\n\n// filter end\n\n// popular property\n.objects-section {\n    padding: 48px 0 0 0;\n\n    .titlesect {\n        @include h1;\n        margin-bottom: 32px;\n        color: var(--primary);\n    }\n}\n\n.objects-section__sortrow {\n    display: flex;\n    align-items: center;\n    margin-bottom: 32px;\n\n    p {\n        @include h6;\n        width: 100%;\n        max-width: calc(100% - 150px);\n        flex: 0 0 calc(100% - 150px);\n        margin: 0;\n        color: var(--primary);\n    }\n\n    .poppropselect {\n        width: 100%;\n        max-width: 150px;\n        flex: 0 0 150px;\n\n        .select2-container {\n            width: 100% !important;\n        }\n\n        .select2-container--default .select2-selection--single {\n            border: none;\n            background: transparent;\n            border-radius: 0;\n        }\n\n        .select2-container--default .select2-selection--single .select2-selection__rendered {\n            @include h6;\n            color: var(--primary);\n        }\n\n        .select2-container--default .select2-selection--single .select2-selection__arrow b {\n            display: none;\n        }\n\n        .select2-container--default .select2-selection--single .select2-selection__arrow {\n            width: 24px;\n            height: 25px;\n            background: url('../img/general/select-arr.svg') no-repeat center / 100%;\n            transition: 0.3s;\n        }\n\n        .select2-container--default.select2-container--open .select2-selection--single .select2-selection__arrow {\n            transform: rotate(-180deg);\n        }\n    }\n}\n\n.objectcard {\n    aspect-ratio: 1 / 1;\n    position: relative;\n    border-radius: 16px;\n    overflow: hidden;\n    display: flex;\n    align-items: flex-end;\n    justify-content: center;\n    padding-bottom: 9px;\n    margin-bottom: 16px;\n\n    img {\n        width: 100%;\n        height: 100%;\n        object-fit: cover;\n        object-position: 50% 50%;\n        position: absolute;\n        left: 0;\n        top: 0;\n        transition: 0.5s;\n        transform: scale(1.01);\n    }\n\n    &:hover {\n        img {\n            transform: scale(1.1);\n        }\n    }\n\n    .objectcard__info {\n        border-radius: 12px;\n        padding: 12px;\n        background: rgba(#3D3743, 0.96);\n        z-index: 2;\n        width: calc(100% - 16px);\n\n    }\n}\n\n.objectcard__info-header {\n    margin-bottom: 12px;\n    position: relative;\n\n    &::after {\n        content: '';\n        display: inline-block;\n        width: 28px;\n        height: 28px;\n        background: url('../img/main/obj-arrow.svg') no-repeat center / 100%;\n        position: absolute;\n        right: 0;\n        top: 3px;\n\n    }\n\n    .title {\n        @include h6;\n        margin: 0;\n        color: #fff\n    }\n\n    p {\n        @include body3;\n        color: #fff;\n        margin: 0;\n\n    }\n}\n\n.objectcard__info-body {\n    display: flex;\n    flex-wrap: wrap;\n    align-items: center;\n\n    .descrbox {\n        position: relative;\n        width: 100%;\n        text-align: center;\n        padding: 0 3px;\n\n\n        &::after {\n            content: '';\n            display: inline-block;\n            border-radius: 8px;\n            background: var(--gray);\n            width: 1px;\n            height: 24px;\n            position: absolute;\n            right: 0;\n            top: 50%;\n            transform: translateY(-50%);\n        }\n\n        &:last-child {\n            &::after {\n                display: none;\n            }\n        }\n\n        p {\n            @include body3;\n            color: var(--gray);\n\n            span {\n                display: block;\n                color: #fff;\n                margin-bottom: 2px;\n            }\n        }\n\n        &.descrbox__beds {\n            max-width: 20%;\n            flex: 0 0 20%;\n        }\n\n        &.descrbox__baths {\n            max-width: 23%;\n            flex: 0 0 23%;\n        }\n\n        &.descrbox__price {\n            max-width: 23%;\n            flex: 0 0 23%;\n        }\n\n        &.descrbox__type {\n            max-width: 34%;\n            flex: 0 0 34%;\n            text-align: left;\n            padding-left: 10px;\n\n            p {\n                color: #fff;\n            }\n        }\n\n    }\n}\n\n.loadmore {\n    display: inline-block;\n    margin-top: 50px;\n    color: var(--primary);\n    font-size: 16px;\n    font-family: \"Libre Franklin\", sans-serif;\n    cursor: pointer;\n    position: relative;\n    line-height: 100%;\n\n    &::after {\n        content: '';\n        display: block;\n        height: 1px;\n        width: 0;\n        transition: 0.5s;\n        background: var(--primary);\n        position: absolute;\n        left: 0;\n        bottom: -2px;\n    }\n\n    &:hover {\n        &::after {\n            width: 100%;\n        }\n    }\n}\n\n// CONTACT SECTION\n.contactsection {\n    padding: 98px 0 80px;\n}\n\n.contactsection__left {\n    .title {\n        @include h1;\n        color: var(--primary);\n        margin-bottom: 16px;\n        max-width: 100%;\n    }\n\n    p {\n        max-width: 400px;\n        @include body1;\n        color: var(--primary);\n        margin-bottom: 48px;\n    }\n\n    ul {\n        list-style-type: none;\n        margin: 0;\n        padding: 0;\n\n        li {\n            display: flex;\n            flex-wrap: wrap;\n            align-items: center;\n            margin-bottom: 32px;\n\n            .imgwrap {\n                width: 100%;\n                max-width: 70px;\n                flex: 0 0 70px;\n\n                img {\n                    width: 100%;\n                    vertical-align: top;\n                }\n            }\n\n            .rightinfo {\n                width: 100%;\n                max-width: calc(100% - 70px);\n                flex: 0 0 calc(100% - 70px);\n                padding-left: 32px;\n\n                p {\n                    margin-bottom: 8px;\n                    @include body2;\n                    color: var(--primary);\n                }\n\n                a {\n                    @include body1;\n                    color: var(--primary);\n                    transition: 0.3s;\n\n                    &:hover {\n                        color: var(--accent);\n                    }\n                }\n            }\n        }\n    }\n}\n\n.contactsection__right {\n    padding-left: 30px;\n}\n\n.formdark {\n    background: var(--secondary);\n    border-radius: 22px;\n    padding: 40px 32px;\n\n    .inputfield {\n        margin-bottom: 24px;\n\n        label {\n            @include h5;\n            display: block;\n            margin-bottom: 8px;\n            color: var(--gray);\n        }\n\n        input,\n        textarea {\n            width: 100%;\n            height: 54px;\n            border-radius: 12px;\n            background: #48484A;\n            padding-left: 12px;\n            color: #EEEEEE;\n            border: none;\n            font-size: 16px;\n            font-family: \"Libre Franklin\", sans-serif;\n            transition: 0.3s;\n\n            &:focus {\n                background: #3D3743;\n            }\n\n            &:not(:placeholder-shown) {\n                background: #3D3743;\n            }\n\n            &::placeholder {\n                color: var(--gray);\n            }\n        }\n\n        textarea {\n            resize: none;\n            height: 120px;\n            padding-top: 15px;\n            outline: none;\n            vertical-align: top;\n        }\n    }\n\n    .submbtn {\n        width: 100%;\n        background: var(--accent);\n        height: 50px;\n        border-radius: 16px;\n        border: none;\n        transition: 0.3s;\n        cursor: pointer;\n        color: #fff;\n        font-size: 16px;\n        font-weight: 500;\n        font-family: \"Libre Franklin\", sans-serif;\n\n        &:hover {\n            background: #fff;\n            color: var(--accent);\n        }\n    }\n}\n\n.objectcard__info-header {\n    padding-right: 30px;\n}\n\n@media(max-width:1439.8px) {\n    .pagesideline {\n        width: 75px;\n    }\n\n    .containersect {\n        padding-left: 75px;\n        padding-right: 75px;\n    }\n\n    .welcomesection {\n        padding-top: 75px;\n    }\n\n    .welcomesection .imgwrap {\n        height: calc(100vh - 120px);\n    }\n\n    .languagelist li a {\n        padding: 4px 6px;\n        font-size: 15px;\n    }\n\n    .welcomesection .welcomesection__scrollarr img {\n        width: 50px;\n    }\n\n    .objects-section .titlesect {\n        margin-bottom: 20px;\n    }\n\n    .objectcard__info-header {\n        margin-bottom: 5px;\n    }\n\n    .objectcard .objectcard__info {\n        border-radius: 8px;\n        padding: 8px;\n    }\n\n    .filter-section__header ul li button {\n        height: 50px;\n    }\n\n    .filter-section__body {\n        padding-top: 3px;\n    }\n\n    .filter__searchbox {\n        margin-bottom: 20px;\n    }\n\n    .loadmore {\n        margin-top: 30px;\n    }\n\n    .contactsection__left p {\n        margin-bottom: 30px;\n    }\n\n    .contactsection__left ul li .imgwrap {\n        max-width: 50px;\n        flex: 0 0 50px;\n    }\n\n    .contactsection__left ul li .rightinfo {\n        max-width: calc(100% - 50px);\n        flex: 0 0 calc(100% - 50px);\n        padding-left: 20px;\n    }\n\n    .contactsection__left ul li .rightinfo p {\n        margin-bottom: 5px;\n    }\n\n    .contactsection__left ul li {\n        margin-bottom: 20px;\n    }\n\n    .objectcard__info-body .descrbox.descrbox__type {\n        padding-left: 5px;\n    }\n\n    .formdark .inputfield {\n        margin-bottom: 16px;\n\n        input {\n            height: 48px;\n            border-radius: 8px;\n        }\n    }\n\n    .formdark {\n        border-radius: 15px;\n        padding: 30px;\n    }\n\n    .contactsection {\n        padding-top: 70px;\n    }\n\n\n    .objects-section .titlesect,\n    .contactsection__left .title {\n        font-size: 40px;\n    }\n\n    .formdark .inputfield label {\n        font-size: 16px;\n    }\n\n    .objectcard__info-header .title {\n        font-size: 14px;\n    }\n\n}\n\n@media(max-width:1199.8px) {\n\n    .welcomesection .imgwrap {\n        height: auto;\n    }\n\n    .welcomesection .welcomesection__scrollarr {\n        bottom: 20px;\n    }\n\n    .fscontent__type,\n    .fscontent__bb,\n    .fscontent__price {\n        max-width: 33.333%;\n        flex: 0 0 33.333%;\n        padding-right: 10px;\n        margin-bottom: 20px;\n    }\n\n    .fscontent__loc {}\n\n    .fscontent__price .ddmenu.show {\n        left: initial;\n        right: 5px;\n    }\n\n}\n\n@media(max-width:991.8px) {\n\n    .pagesideline {\n        display: none;\n    }\n\n    .welcomesection .welcomesection__scrollarr {\n        display: none;\n    }\n\n    .containersect {\n        padding-left: 25px;\n        padding-right: 25px;\n    }\n\n    .filter-section {\n        padding-top: 10px;\n    }\n\n    .filter-sectionwrap {\n        margin-top: 40px;\n    }\n\n    .fscontent__type,\n    .fscontent__bb,\n    .fscontent__price,\n    .fscontent__loc {\n        max-width: 50%;\n        flex: 0 0 50%;\n    }\n\n    .fscontent__btn {\n        max-width: 100%;\n        flex: 0 0 100%;\n        margin-top: 10px;\n    }\n\n    .fscontent__price .ddmenu.show {\n        left: 0;\n        right: initial;\n    }\n\n    .select2-container--default .select2-selection--single .select2-selection__rendered {\n        padding-left: 0;\n    }\n\n    .objectcard__info-header .title {\n        font-size: 16px;\n    }\n\n    .objectcard__info-header {\n        margin-bottom: 10px;\n    }\n\n    .contactsection__right {\n        padding-left: 0;\n    }\n\n    .formdark .submbtn {\n        margin-top: 20px;\n    }\n\n    .contactsection__left ul {\n        display: flex;\n\n        li {\n            width: 100%;\n            max-width: 33.333%;\n            flex: 0 0 33.333%;\n        }\n    }\n\n    .contactsection__left {\n        margin-bottom: 20px;\n    }\n\n    .contactsection__left p {\n        max-width: 100%;\n    }\n\n    .welcomesection {\n        padding-top: 100px;\n    }\n\n\n\n\n    .objects-section .titlesect,\n    .contactsection__left .title {\n        font-size: 32px;\n    }\n\n    .fscontent__btn input,\n    .welcomesection .imgwrap,\n    .filter__searchbox input {\n        border-radius: 8px;\n    }\n\n}\n\n@media(max-width:767.8px) {\n    .contactsection__left ul {\n        flex-wrap: wrap;\n\n        li {\n            max-width: 100%;\n            flex: 0 0 100%;\n        }\n    }\n}\n\n@media(max-width:575.8px) {\n    .filter-section__header ul {\n        flex-wrap: wrap;\n        padding: 10px 0;\n\n        li {\n            width: 100%;\n            max-width: 25%;\n            flex: 0 0 25%;\n\n            button {\n                width: 100%;\n                padding: 0;\n                height: auto;\n                min-width: initial;\n            }\n        }\n    }\n\n    .containersect {\n        padding-left: 12px;\n        padding-right: 12px;\n    }\n\n    .welcomesection {\n        padding-top: 85px;\n    }\n\n    .filter-sectionwrap {\n        margin-top: 30px;\n    }\n\n    .filter__searchbox input {\n        height: 46px;\n        padding-left: 40px;\n    }\n\n    .filter__searchbox .search-ic {\n        width: 20px;\n        left: 10px;\n    }\n\n    .filter-section {\n        border-radius: 10px;\n    }\n\n    .filter__searchboxwrap {\n        padding: 0 10px;\n    }\n\n    .fscontent__type,\n    .fscontent__bb,\n    .fscontent__price,\n    .fscontent__loc {\n        max-width: 100%;\n        flex: 0 0 100%;\n        margin-bottom: 10px;\n        border-bottom: 1px solid #dfdfdf;\n        padding-bottom: 10px;\n\n        &::after {\n            display: none;\n        }\n    }\n\n    .fscontent__type {\n        padding-left: 0;\n        padding-right: 0;\n    }\n\n    .ddmenu,\n    .ddmenu.price {\n        width: 100%;\n        left: 0;\n        right: initial;\n        margin-left: 0;\n        margin-right: 0;\n        top: 40px;\n    }\n\n    .ddprce-col .inputfield input {\n        height: 42px;\n        padding-left: 37px;\n    }\n\n    .ddprce-col .inputfield span {\n        font-size: 12px;\n    }\n\n    .ddprce-col button {\n        border-radius: 8px;\n        height: 42px;\n    }\n\n    .styledselect__wrap .select2 {\n        padding: 0 10px;\n    }\n\n    .styledselect__wrap .select2-container--default .select2-selection--single .select2-selection__arrow {\n        right: 10px;\n    }\n\n    .fscontent__btn input {\n        height: 42px;\n    }\n\n    .objects-section__sortrow {\n        margin-bottom: 10px;\n    }\n\n    .objects-section__sortrow .poppropselect .select2-container--default .select2-selection--single .select2-selection__rendered {\n        font-size: 14px;\n    }\n\n    .objects-section__sortrow .poppropselect {\n        max-width: 130px;\n    }\n\n    .objects-section__sortrow p {\n        max-width: calc(100% - 130px);\n        flex: 0 0 calc(100% - 130px);\n    }\n\n    .formdark {\n        padding: 30px 20px;\n    }\n\n    .formdark .inputfield input {\n        height: 42px;\n    }\n\n    .formdark .submbtn {\n        margin-top: 10px;\n    }\n\n    .contactsection {\n        padding-bottom: 50px;\n    }\n\n\n\n    .objectcard__info-header .title {\n        font-size: 18px;\n    }\n\n    .objects-section__sortrow p {\n        font-size: 14px;\n    }\n\n    .objects-section .titlesect,\n    .contactsection__left .title {\n        font-size: 24px;\n    }\n}"
        }
    ]
}